<?xml version="1.0" encoding="UTF-8"?>
<objects serializationModel="Studio.02.02.00">
	<object class="EncodingSetting" id="{152e423c-4c60-4a0d-844a-a6cfebeedf74}">
		<property name="encodingFormat">
			<value>3</value>
		</property>
		<property name="quality">
			<value>70</value>
		</property>
		<relationship name="platform">
			<destination>{bb6eea52-ab76-4681-ad97-09c40eff6d19}</destination>
		</relationship>
		<relationship name="encodable">
			<destination>{e56d28f6-8925-4298-8f6f-1841b65815f3}</destination>
		</relationship>
	</object>
</objects>
